{
    "jdbcconnection": [
        {
            "name": "OAuth",
            "enabled": "true",
            "properties": {
                "property": [
                    {
                        "key": "maximumPoolSize",
                        "integerValue": "15"
                    },
                    {
                        "key": "minimumPoolSize",
                        "integerValue": "3"
                    }
                ]
            },
            "extension": {
                "driverClass": "com.mysql.cj.jdbc.Driver",
                "jdbcUrl": "jdbc:mysql:\/\/l7gw-10444-db:3307\/ssg",
                "connectionProperties": {
                    "property": [
                        {
                            "key": "EnableCancelTimeout",
                            "stringValue": {
                                "value": "true"
                            }
                        },
                        {
                            "key": "password",
                            "stringValue": {
                                "value": "$L7C2$1,ngh3I32ee146BM+8YC2h58Gcp+xbwTfHOAkXcvJ+2+I=$egYZ2+ylpeXHlaJ4WsWPs0R7AsKQ77z7zYZR4DUa11FEfVG+T3iaeQUx5zSTo9PCw53TUQknWlMss6i01pQn1Q==",
                                "bundleKey": "$L7C2$9fa1f,bwS2aIL5q51zz+vEWOqvxbLdW8m5znoQAvD\/a8T7U9g=$KoknBtWm2\/s1Hy4Iy1jGeB1UBA6t7EzZftzHUxvwh92szNMqsBN2jOm\/dl4BWPOitdGwFwbtux5Gp51vp7tx9KKbOatxiCUIZ3o3XjdMklDf30prpIWl9ATE\/hknW1B+"
                            }
                        },
                        {
                            "key": "user",
                            "stringValue": {
                                "value": "root"
                            }
                        }
                    ]
                }
            },
            "id": "cedabd7f249c1123eba3677b08cb1b1a"
        }
    ]
}